LICENSE
MANIFEST.in
README.md
scrapy.cfg
setup.cfg
setup.py
os_scrapy_httpproxy_middleware/__init__.py
os_scrapy_httpproxy_middleware/items.py
os_scrapy_httpproxy_middleware/middlewares.py
os_scrapy_httpproxy_middleware/pipelines.py
os_scrapy_httpproxy_middleware/settings.py
os_scrapy_httpproxy_middleware.egg-info/PKG-INFO
os_scrapy_httpproxy_middleware.egg-info/SOURCES.txt
os_scrapy_httpproxy_middleware.egg-info/dependency_links.txt
os_scrapy_httpproxy_middleware.egg-info/not-zip-safe
os_scrapy_httpproxy_middleware.egg-info/requires.txt
os_scrapy_httpproxy_middleware.egg-info/top_level.txt
os_scrapy_httpproxy_middleware/spiders/__init__.py
requirements/requirements-lint.txt
requirements/requirements-test.txt
requirements/requirements.txt
tests/__init__.py
tests/test_scrapy_check.py